termgame/__init__.py
termgame/logger.py
termgame/settings.py
termgame/util.py
termgame/base/__init__.py
termgame/base/engine.py
termgame/base/gameobject.py
termgame/base/physics_engine.py
termgame/base/physics_gameobject.py
termgame/graphics/__init__.py
termgame/graphics/pixel.py
termgame/graphics/screen.py
termgame-0.0.4.dist-info/LICENSE
termgame-0.0.4.dist-info/METADATA
termgame-0.0.4.dist-info/WHEEL
termgame-0.0.4.dist-info/top_level.txt
termgame-0.0.4.dist-info/RECORD
