Metadata-Version: 2.1
Name: termgame
Version: 0.0.4
Summary: Terminal-based graphical game engine
Home-page: UNKNOWN
Author: Gregory Glatzer
Author-email: gregoryg323@gmail.com
License: UNKNOWN
Platform: UNKNOWN
License-File: LICENSE
Requires-Dist: Colr (==0.9.1)
Requires-Dist: cursor (==1.3.5)
Requires-Dist: keyboard (==0.13.5)
Requires-Dist: numpy (==1.22.3)
Requires-Dist: Pillow (==9.3.0)
Requires-Dist: pymunk (==6.4.0)
Requires-Dist: python-dotenv (==0.21.0)
